{"metadata": [{"year": "2016", "description": "Il s\u2019appelle Vermont Washington. Si son patronyme est symbole de libert\u00e9 pour l\u2019Am\u00e9rique, il ne l\u2019est pas pour lui, jeune afro-africain. \nIl habite \u00e0 Los Angeles, dans le quartier de Watts, c\u00e9l\u00e8bre pour les \u00e9meutes survenues, en ao\u00fbt 1965, \u00e0 la suite du 100\u00e8 anniversaire de l\u2019abolition de l\u2019esclavage aux Etats-Unis. \nSon quotidien, et celui de sa famille, n\u2019est fait que d\u2019injustices, de restrictions, de discriminations et d\u2019humiliation. Ils sont victimes du racisme ordinaire, qui s\u00e9vit encore en ces ann\u00e9es soixante, o\u00f9 le Ku Klux Klan, vestige insupportable de l\u2019esclavage, n\u2019en finit pas de mourir. Une haine omnipr\u00e9sente per\u00e7ue \u00e0 travers le travail, l\u2019\u00e9ducation, les lieux publics\u2026 M\u00eame les forces de l\u2019ordre soudoy\u00e9es participent \u00e0 cette discrimination g\u00e9n\u00e9rale.\nC\u2019est donc avec le Black Panther Party, mouvement r\u00e9volutionnaire afro-am\u00e9ricain dont il est membre, que Vermont Washington entend lutter, entour\u00e9 de ses amis (Noirs), pour leurs droits \u00e0 l\u2019\u00e9galit\u00e9. \nCependant, Pete, son meilleur ami Blanc, qui pourtant soutient le parti, le pousse \u00e0 \u00eatre raisonnable, craignant qu\u2019il ne finisse en prison. Son p\u00e8re, chez qui il vit avec sa famille, ayant choisi de faire profil bas, se heurte violemment \u00e0 lui, lui conseillant de se soumettre. Quant \u00e0 sa femme impuissante, elle vit dans la peur qu\u2019il ne se fasse tuer \u00e0 tout moment.\nDe provocations racistes en humiliations permanentes, le destin de Vermont Washington est rythm\u00e9 par le programme en dix points des Black Panthers : ils luttent pour la libert\u00e9, le plein emploi, pour que le peuple Noir ne soit plus vol\u00e9 par la capitalisme, pour des logements d\u00e9cents, l\u2019\u00e9ducation\u2026 \n\n\n", "type": "comicSeries", "publisher": "Futuropolis", "name": "Motherfucker"}]}