{"metadata": [{"type": "comicSeries", "publisher": "MediBang(global)", "year": "2018", "description": "Mr. Iori is a divorced single dad and has a son who\u2019s in kindergarten. To comfort him\uff0c Mr. Iori\u2019s subordinate\uff0c Hayakawa\uff0c prepares him a delicious lunch. Mr. Iori is flattered by the daring approach from the young and handsome Hayakawa\uff0c but...... This is a compilation of bittersweet love stories that play on the theme of adult sensibilities.", "name": "Daddy's Boyfriend (Yaoi Manga)"}]}