{"metadata": [{"year": "2018", "description": "Le permis ? Une formalit\u00e9 ! Le permis c'est quoi au juste ? Une s\u00e9rie de diapositives de vacances auxquelles il faut r\u00e9pondre au hasard suivi d'une balade en voiture avec un examinateur qui vous fait visiter la r\u00e9gion ? Et c'est \u00e7a qui vous fait peur ?! Dans ce cas, ce livre vous apportera tout ce dont vous avez besoin pour r\u00e9ussir votre permis sans difficult\u00e9 et presque sans accident : tests, conseils, mises en situation...", "type": "comicSeries", "publisher": "Jungle", "name": "Le permis sans se fouler"}]}