{"metadata": [{"year": "2017", "description": "Il a fui un pass\u00e9 qui n'\u00e9tait pas le sien.\n\nUn fils revient au pays apr\u00e8s 25 ans sans avoir donn\u00e9 la moindre nouvelle \u00e0 ses parents qu'il a quitt\u00e9s brutalement pour entrer dans l'arm\u00e9e. \u00ab Vir\u00e9 \u00bb d'Indochine par le Vietminh, il a fini par s'installer pr\u00e8s de \u00ab chez lui \u00bb, sans pour autant renouer vraiment avec son p\u00e8re, veuf, qui vit encore dans ses collines des C\u00e9vennes. C'est \u00e0 la faveur des terribles inondations de 1958 qu'ils vont se reparler, remonter le temps, refaire l'histoire, leur histoire.", "type": "comicSeries", "publisher": "Bamboo", "name": "L'\u00eele aux remords"}]}