{"metadata": [{"year": "2019", "description": "De \u00abMadame Bovary\u00bb \u00e0 \u00abCrime et Ch\u00e2timent\u00bb en passant par \u00abL'Illiade\u00bb ou \u00abLe Quart Livre\u00bb, Patrique, simple motte de terre ayant surv\u00e9cu gr\u00e2ce \u00e0 la lecture, nous pr\u00e9sente ses chroniques lit\u00e9raires. O\u00f9 l'on d\u00e9couvre Emma Bovary comme une \u00abno life\u00bb prenant des amants pour conjurer son ennui, o\u00f9 l'on apprend comment Agatha Christie, habitu\u00e9e des scandales, donne toujours aux femmes des r\u00f4les-cl\u00e9s, ou encore pourquoi \u00abClaudine \u00e0 l'\u00e9cole\u00bb, malgr\u00e9 son titre \u00abcalcul\u00bb, est un livre dr\u00f4le et tr\u00e8s coquin... Quand Madame Bovary rencontre Achille au pied l\u00e9ger.\n", "type": "comicSeries", "publisher": "Gallimard", "name": "Les Classiques de Patrique"}]}