{"metadata": [{"name": "Louna et sa m\u00e8re", "year": "2013", "description": "En voil\u00e0 un couple moderne ! Louna et sa m\u00e8re vivent seules ensemble, entre doudous et questions insolubles, \u00e9cran plasma et nouvel amoureux. Elev\u00e9e \u00e0 la mode 2000, Louna raisonne et \" verbalise \", comme sa m\u00e8re. Sauf qu'\u00e0 son \u00e2ge, \u00e7a ne rend pas pareil... Alors maman, on \" g\u00e8re \" ? Derri\u00e8re Louna et sa m\u00e8re, se cachent les enfants que vous avez fabriqu\u00e9s et les parents que vous \u00eates devenus... Retrouvez-les !", "publisher": "Akileos", "type": "comicSeries"}]}