{"metadata": [{"type": "comicSeries", "publisher": "Zenescope", "year": "2011", "description": "Zenescope's second book under its new all ages imprint, Silver Dragon Books, takes you on an adventure back in time with Discovery Channel's Dinosaurs & Prehistoric Predators. Nothing captures the imagination of kids like the prehistoric world of dinosaurs and this book has all their favorites. Velicoraptors, Triceratops, and T-Rex all come to life in this exciting and groundbreaking new graphic novel. A must have book for dinosaur fans of all ages.", "name": "Dinosaurs and Prehistoric Predators"}]}