{"metadata": [{"publisher": "Le Lombard", "year": "2017", "type": "comicSeries", "description": "7 f\u00e9vrier 2017. La station lunaire internationale ne r\u00e9pond plus. Et pour cause : un monstrueux extra-terrestre s'est r\u00e9veill\u00e9, annihilant toute vie alentour ! Mais ce massacre n'est que la partie \u00e9merg\u00e9e d'un iceberg qui va frapper la Terre de plein fouet : en cinq endroits, autant de cr\u00e9atures dot\u00e9es de terribles pouvoirs sortent de leur sommeil s\u00e9culaire. L'humanit\u00e9 n'\u00e9tait pas pr\u00eate... \u00e0 l'exception d'Helius, myst\u00e9rieux humano\u00efde qui semble conna\u00eetre ces extra-terrestres depuis longtemps, tr\u00e8s longtemps...", "name": "World War X"}]}