{"metadata": [{"year": "2019", "description": "Une qu\u00eate initiatique \u00e0 la Dragon Ball dans une ambiance \u00e0 la Miyazaki par des auteurs incroyablement cr\u00e9atifs et tr\u00e8s suivis par une grande communaut\u00e9 sur Internet.\nL'\u00e9quilibre de la plan\u00e8te Topo\u00ef est chamboul\u00e9 par l'arriv\u00e9e d'envahisseurs venus de l'espace. Ces buzards ravagent tout sur leur passage. Ils sont en qu\u00eate d'une force myst\u00e9rieuse, l'Ultralazer, intimement li\u00e9e au Roi des b\u00eates, v\u00e9ritable dieu vivant, garant de l'\u00e9quilibre de toutes choses. Horb et Bouko, les gardiens et serviteurs attitr\u00e9s de ce dernier, organisent la r\u00e9sistance.\n", "type": "comicSeries", "publisher": "Delcourt", "name": "Ultralazer"}]}