{"metadata": [{"year": "2018", "description": "Je vais chez Raymond, mon voisin d'\u00e0 c\u00f4t\u00e9. Il n'y a qu'un bout de bois \u00e0 traverser, et on arrive dans un petit hameau o\u00f9 n'habitent plus que son fr\u00e8re et lui maintenant. La petite maison o\u00f9 il vit, c'est celle o\u00f9 \u00e9tait son p\u00e8re les derni\u00e8res ann\u00e9es. Un sacr\u00e9 gaillard celui-l\u00e0, qui ne voulait voir personne. Il y a deux pi\u00e8ces, une petite grange, un jardin et un verger derri\u00e8re, o\u00f9 Raymond mettait des poules, mais comme avec les maladies nouvelles, il faut les enfermer, il a arr\u00eat\u00e9 les poules. C'est comme \u00e7a. C'est assez pour vivre.\n", "type": "comicSeries", "publisher": "Futuropolis", "name": "Mon voisin Raymond"}]}