{"metadata": [{"publisher": "Marvel", "year": "2018", "type": "comicSeries", "description": "Collects Quicksilver: No Surrender #1-5.\n\nThe fastest Avenger of all races straight out of the smash-hit \u201cNo Surrender\u201d event and into a psychedelic survival thriller unlike anything you\u2019ve seen before! Quicksilver\u2019s super-speed and abrasive personality have always isolated him, but he\u2019s never been truly alone\u2026until now. Trapped beyond the perception of his friends, family and allies, Pietro must now wage a one-man guerilla war against a monster that he\u2019s not even sure is real \u2014 to save a world that he may never be a part of again! But can he protect his sister, the Scarlet Witch, from forces she can\u2019t even perceive? Exhausted and facing an enemy who renders his abilities useless, Pietro must use every trick in his arsenal to save Wanda\u2026but he\u2019s running out of tricks! Is Quicksilver doomed to be lost forever?\n", "name": "Quicksilver: No Surrender"}]}