{"metadata": [{"publisher": "Les Humano\u00efdes Associ\u00e9s", "year": "2015", "type": "comicSeries", "description": "Un jour, Gr\u00e9goire d\u00e9couvre un m\u00e9daillon cach\u00e9 dans la chambre de sa nouvelle demeure.  L'\u00e9trange objet va lui ouvrir les portes d'un monde oubli\u00e9 de tous, o\u00f9 la magie r\u00e8gne encore...Gr\u00e9goire est dot\u00e9 d'un Talisman particulier, qui lui permet de voyager dans le temps.  Il se rend ainsi dans le pass\u00e9, au XVIIe si\u00e8cle, o\u00f9 se r\u00e9alisent ses r\u00eaves d'aventures extraordinaires : les gargouilles s'animent pour devenir de vrais dragons et il suit une formation pour devenir magicien et lutter contre les forces de la magie noire...", "name": "Gargouilles"}]}