{"metadata": [{"publisher": "Marvel", "year": "2001", "type": "comicSeries", "description": "Collects Fantastic Four: World's Greatest Comics Magazine #1-12.\n\nStan Lee and Jack Kirby's legendary run on FANTASTIC FOUR lasted more than one hundred issues \u2014 and ended all too soon! Now, witness the continuing adventures of Marvel's First Family, told as if Stan and Jack never left the book! Some of comics' most talented creators join forces in this time-tossed tribute to the original Imaginauts! Featuring Doctor Doom, the Avengers, the X-Men, Thor, the Hulk, Daredevil, Black Panther, the Inhumans, the Sub-Mariner, the Silver Surfer, M.O.D.O.K., Annihilus and more! It's an action-packed celebration of everything that made Stan and Jack's FANTASTIC FOUR truly the World's Greatest Comics Magazine!\n", "name": "Fantastic Four: The World's Greatest Comics Magazine"}]}