{"metadata": [{"year": "2014", "description": "La guerre n'est pas qu'un jeu\n\nSoci\u00e9t\u00e9 militaire priv\u00e9e de seconde zone, apparue en Serbie sur les ruines de la derni\u00e8re guerre en 2021, Kali n'a rien d'une grande entreprise militaire. Les mercenaires employ\u00e9s n'y ont pas une grande esp\u00e9rance de vie ! Mais la bo\u00eete a ses avantages, dont un recrutement laxiste qui permet au myst\u00e9rieux Damien Marik d'\u00eatre leur nouveau pilote de Mech, ces tanks modernes dont les Balkans furent le premier terrain d'exercice. \u00c0 peine arriv\u00e9, Marik est recrut\u00e9 pour une mission apparemment anodine : escorter un marchand d'armes au c\u0153ur de la base des insurg\u00e9s. Quand The Shield et Les 12 Salopards rencontrent Jason Bourne ! R\u00e9cit d'anticipation nourri aux s\u00e9ries am\u00e9ricaines et aux jeux vid\u00e9os, Seigneurs de Guerre est une critique en creux des conflits modernes autant qu'une formidable s\u00e9rie de guerre m\u00e2tin\u00e9e de thriller politique.", "type": "comicSeries", "publisher": "Gl\u00e9nat", "name": "Seigneurs de guerre"}]}