{"metadata": [{"publisher": "Marvel", "year": "2017", "type": "comicSeries", "description": "Collects Runaways (2017) #1-6.\n\nThe \"it\" book of the early 2000s is back, with the original cast \u2014 Nico! Karolina! Molly! Chase! Old Lace! And could it be\u2026Gert?! The heart of the Runaways died years ago \u2014 but you won't believe how she returns! Superstar author Rainbow Rowell teams with fan-favorite artist Kris Anka to revive the series you can rely on to shock you and break your heart! Did Chase and Gert's love survive their time apart? Have Karolina and Nico's feelings made their friendship impossible? And should you be more worried about the emotional land mines lying in wait \u2014 or the shadowy scientist watching the ragtag group from a distance? Plus: What's in Chase's backpack? And what's up with Princess Powerful, A.K.A. the best Marvel character of all time, Molly Hayes?!\n", "name": "Runaways"}]}