{"metadata": [{"type": "comicSeries", "publisher": "Soleil", "year": "2014", "description": "IL ETAIT UNE FOIS SUR LE MONDE DE TROY LA FORTERESSE DE NUIT SAFRAN...Elle se dresse depuis des si\u00e8cles au nord de l'H\u00e9dulie sur une terre caillouteuse battue par les vents et la pluie. La vie y est rude et inhospitali\u00e8re. Comme dans toutes les baronnies, on s'y distrait le plus sainement du monde en guerroyant avec fougue et hardiesse contre ses voisins, en l'occurence Roq-Bl\u00eame et Bastillac. Mais un jour, les spectres des illustres anc\u00eatres de la famille envahissent la contr\u00e9e ! Une exp\u00e9rience \u00e0 vrai dire assez d\u00e9sagr\u00e9able pour tout le monde. Ainsi commence la l\u00e9gende de Libbelule de Nuit Safran, troisi\u00e8me enfant du Baron \u00e9ponyme, \u00e0 qui il incombe la t\u00e2che de ramener la paix dans le royaume et les morts dans leurs cercueils.\n", "name": "Legendes de Troy"}]}