{"metadata": [{"year": "2010", "description": "La tour Pondich\u00e9ry est en construction : un chantier vertical de prestige, qui pousse peu \u00e0 peu dans le ciel de la ville... ou plut\u00f4t, qui devrait pousser ! Car la sympathique \u00e9quipe d'ouvriers qui s'y active n'est pas la plus efficace, surtout ceux \"du sommet\", de vrais pieds-nickel\u00e9s... Et le futur gratte-ciel de 80 \u00e9tages plafonne encore et toujours au 31e, au grand d\u00e9sespoir des investisseurs et des responsables du chantier !Laissez-vous prendre par le vertige de l'humour du Chantier, un recueil de gags garanti sans mauvaises chutes !", "type": "comicSeries", "publisher": "Bamboo", "name": "Le Chantier"}]}