{"metadata": [{"publisher": "La Musardine Dynamite", "year": "2015", "type": "comicSeries", "description": "Incarnation se r\u00eave top-mod\u00e8le mais son physique ne correspond pas aux crit\u00e8res du mannequinat d\u2019aujourd\u2019hui. Trop charnue, lui reproche-t-on. Alors, face \u00e0 tant de cruaut\u00e9s, la jeune Ib\u00e9rique prend le taureau par les cornes et d\u00e9cide de maigrir co\u00fbte que co\u00fbte. Sa corrida commence par la prise de pilules coupe-faim qui provoquent moins la perte de poids qu\u2019une libido d\u00e9mesur\u00e9e\u2026\n\nAvec La Di\u00e8te, Ignacio No\u00e9 brocarde joyeusement une profession qui pr\u00f4ne la malnutrition comme r\u00e8gle de vie et donne \u00e0 adorer des totems sans reliefs. Cette satire est \u00e9videmment domin\u00e9e par de longues sc\u00e8nes sexu\u00e9es \u00e0 travers lesquelles l\u2019h\u00e9ro\u00efne red\u00e9couvre les joies sublimes de l\u2019orgasme : Raaaah Lovely !\n", "name": "La Di\u00e8te"}]}