{"metadata": [{"year": "2017", "description": "Le R\u00eaveur est un r\u00e9cit semiautobiographique de Will Eisner, dans lequel il d\u00e9peint l'industrie du comics de la fin des ann\u00e9es 30. Tout au long de son parcours, il fait la rencontre de personnages qui partagent sa passion. Ce r\u00e9cit est \u00e9galement une r\u00e9flexion des plus pertinentes \u2013 car v\u00e9cue de l'int\u00e9rieur \u2013 sur les premiers pas des comic books am\u00e9ricains. On reconna\u00eet parmi les (futurs) auteurs crois\u00e9s par Eisner quelques \"monstres sacr\u00e9s\" comme Bob Kane (Batman), Jack Kirby (The X-Men...), Lou Fine (The Black Condor) et bien d'autres...", "type": "comicSeries", "publisher": "Delcourt", "name": "Le R\u00eaveur"}]}