{"metadata": [{"year": "2017", "description": "Aujourd'hui, Philippe f\u00eate son anniversaire. 53 ans, d\u00e9j\u00e0. Sa maison est confortable, ses enfants sont grands, sa m\u00e8re est bavarde, son nouveau v\u00e9lo est magnifique. Une belle tranche de vie, dans la simplicit\u00e9, l'honn\u00eatet\u00e9. Mais celui qui empoisonne le g\u00e2teau, c'est le patron de Philippe quand il lui annonce son licenciement. Victime collat\u00e9rale de la mondialisation, Philippe coule \u00e0 pic. Perd tout, m\u00eame son toit. Mais cette plong\u00e9e au coeur de lui-m\u00eame va lui permettre d'ouvrir son regard sur les autres. Les gens honn\u00eates n'ont rien d'ordinaire.\nChronique de la tragi-com\u00e9die du quotidien, Les gens honn\u00eates marque la rencontre entre deux auteurs r\u00e9unis par la tendresse qu'ils \u00e9prouvent pour leurs personnages. Jean-Pierre Gibrat, au sc\u00e9nario, et Christian Durieux, au dessin, savent faire vibrer \u00e0 l'unisson la parcelle indicible de la cr\u00e9ation romanesque: son humanit\u00e9.", "type": "comicSeries", "publisher": "Dupuis", "name": "Les gens honn\u00eates"}]}