{"metadata": [{"type": "comicSeries", "publisher": "Seven Seas", "year": "2017", "description": "In a strange, alternate version of Tokyo, superhumans walk the streets: aliens, mutants, paranormals, and other impossible creatures. Jiro Hitoyoshi, a human agent in Tokyo's Superhuman Bureau, has dedicated his life to upholding peace and order for all of the city's denizens. Tokyo's got its fair share of villains -- and when the bad guys get to be too much to handle for even the heroes, you can be sure Jiro Hitoyoshi will be on the case!", "name": "Concrete Revolutio"}]}