{"metadata": [{"year": "2016", "description": "Dana Atkinson, une enqu\u00eatrice de l'arm\u00e9e renvoy\u00e9e pour manquement \u00e0 l'honneur, est rappel\u00e9e au Moyen-Orient quand un groupe de techniciens am\u00e9ricains sp\u00e9cialis\u00e9s dans l'exploitation du p\u00e9trole dispara\u00eet dans des circonstances \u00e9tranges. Suite \u00e0 une s\u00e9rie d'incidents sur le site de forage, Dana et l'enqu\u00eateur iraquien avec lequel elle doit collaborer font une d\u00e9couverte inimaginable : un mal mythique a \u00e9t\u00e9 lib\u00e9r\u00e9, mena\u00e7ant toute la r\u00e9gion et la paix pr\u00e9caire qui y maintient l'\u00e9quilibre.", "type": "comicSeries", "publisher": "Ankama", "name": "Burning Fields"}]}