{"metadata": [{"year": "2018", "description": "Le Premier Ordre a \u00e9tendu ses tentacules et pousse la R\u00e9sistance dans ses retranchements. Impossible de se sauver \u00e0 la vitesse de la lumi\u00e8re avec cet ennemi continuellement \u00e0 ses trousses. Cela n'emp\u00eache pas Finn et ses camarades de tenter d'identifier une br\u00e8che chez leur adversaire. Rey, elle, se trouve toujours sur la plan\u00e8te Ahch-To pour convaincre Luke Skywalker de lui enseigner les rudiments de la Force...\n", "type": "comicSeries", "publisher": "Delcourt", "name": "Star Wars - Les derniers Jedi (Jeunesse)"}]}