{"metadata": [{"year": "2014", "description": "Tout commence le jour o\u00f9 Micka\u00efl, fils prodigue, embo\u00eete le pas de son fr\u00e8re F\u00e9dor, le mal aim\u00e9, pour partir \u00e0 la chasse du terrible homme \u00e0 t\u00eate d'ours... Celui-l\u00e0 m\u00eame qui autrefois leur avait pris leur fr\u00e8re bien-aim\u00e9.\nLes deux fr\u00e8res s'enfoncent alors dans la terrifiante for\u00eat des hommes \u00e0 t\u00eate de b\u00eate, explorant les chemins tortueux du courage. Leur soif de vengeance sera-t-elle \u00e9tanch\u00e9e par la mort de la b\u00eate ?\nUn incroyable voyage dans la lign\u00e9e des grands mythes russes.", "type": "comicSeries", "publisher": "Gl\u00e9nat", "name": "L'Ourso"}]}