{"metadata": [{"year": "2016", "description": "D\u00e9couvrez les aventures d'un jeune chasseur de tr\u00e9sors lanc\u00e9 dans une qu\u00eate p\u00e9rilleuse pour lever les secrets de son pass\u00e9 et r\u00e9clamer son h\u00e9ritage. Un r\u00e9gal pour les amateurs de fantasy et de space opera !\n\nCela fait bien longtemps qu'Ori a d\u00e9sert\u00e9 la cit\u00e9 des couleurs. Depuis la myst\u00e9rieuse disparition de son p\u00e8re, le jeune homme m\u00e8ne une vie d'aventures \u00e0 la recherche d'artefacts et de tr\u00e9sors pr\u00e9cieux. Mais, alors qu'un lointain \u00e9missaire du pass\u00e9 resurgit, sa qu\u00eate la plus difficile va se r\u00e9v\u00e9ler \u00eatre celle de ses origines, sur les traces des secrets de la secte rouge d\u00e9cim\u00e9e dont il est l'h\u00e9ritier...\n", "type": "comicSeries", "publisher": "Delcourt", "name": "Les Chroniques du roi vagabond"}]}