{"metadata": [{"type": "comicSeries", "publisher": "Scholastic - Graphix", "year": "2016", "description": "Scatterbrained Cornelius, King of Kazoo, and his intrepid daughter, Bing, explore a mysterious cave at the top of Mount Kazoo. There they discover a famous alchemist named Quaf is planning a dangerous and forbidden experiment. Now Cornelius, Bing, and the brilliant royal inventor Torq must go all out to stop Quaf before his crazy undertaking threatens the entire kingdom.", "name": "The King of Kazoo"}]}