{"metadata": [{"year": "2016", "description": "Et si la mise en route de l'acc\u00e9l\u00e9rateur de particules, le plus puissant jamais construit, cr\u00e9ait un trou noir qui absorbe la lumi\u00e8re ? Plac\u00e9s au coeur de cette hypoth\u00e8se scientifique, un chercheur sp\u00e9cialiste de l'anti-mati\u00e8re et une jeune fille se retrouvent dans d'improbables sous-sols - ceux de l'acc\u00e9l\u00e9rateur ? -, telles deux \u00e2mes errantes. \nPendant ce temps, en surface, l'\u00e9pouse du scientifique et la jumelle de la jeune fille, qui viennent de se rencontrer par le plus grand et le plus tumultueux des hasards, font connaissance. Dans une ville en proie aux \u00e9meutes et autres braquages, que l'absence de jour et la peur engendrent, elles cherchent \u00e0 comprendre ce qui leur arrive.\nLa solitude a toujours fait partie de la vie de la jeune fille. Toute petite d\u00e9j\u00e0, elle s'ennuyait dans son immeuble de 30 \u00e9tages, avec des ruches sur le toit. D\u00e9cal\u00e9e o\u00f9 qu'elle soit, tout lui paraissant incongru, bizarre, \u00e9trange, comme si tout le monde avait eu le manuel d'utilisation sauf elle. Pour rompre la monotonie de sa vie, pour survivre \u00e0 un drame terrible, elle s'est r\u00e9fugi\u00e9e dans un monde parall\u00e8le, dans une r\u00e9alit\u00e9 comme alt\u00e9r\u00e9e. \nAujourd'hui - r\u00e9alit\u00e9 ou fiction ?-, elle s'inqui\u00e8te pour sa jumelle qui dort, depuis trois semaines, d'un sommeil profond que les m\u00e9decins n'expliquent pas... ", "type": "comicSeries", "publisher": "Futuropolis", "name": "Sous-sols"}]}