{"metadata": [{"publisher": "Marvel", "year": "2010", "type": "comicSeries", "description": "You NEVER ask a woman her age...especially when she can bench press tractor trailers! But She-Hulk's big secret is out, because Marvel's celebrating 30 years of the jade giantess and you're invited to the party! Join acclaimed Shulkie scribe Peter David for an anniversary tale unlike any other! And if you're still feeling savage, writer Brian Reed and artist Iban Coello are hosting an after party in honor of the buff bombshell and her most fabulous friends!\n", "name": "She-Hulk: Sensational"}]}