{"metadata": [{"year": "2016", "description": "Tous les ingr\u00e9dients dignes des plus grandes intrigues romanesques se m\u00ealentau sein de cet album compl\u00e8tement d\u00e9cal\u00e9 !D\u00e9couvrons donc un patriarche propri\u00e9taire d\u2019une superbe\u2026 CX Diesel, nomm\u00e9 Harold Gonzal\u00e8s, quatre successeurs possibles \u2013 ses enfants \u2013 et une question centrale qui br\u00fble toutes les l\u00e8vres et fait tourner les t\u00eates : qui va h\u00e9riter de la CX Diesel ???", "type": "comicSeries", "publisher": "Fluide Glacial", "name": "Amour, passion et CX Diesel"}]}