{"metadata": [{"year": "2013", "description": "Emmet Gardner, la quarantaine, est garde-fronti\u00e8re le long du R\u00edo Grande aux \u00c9tats-Unis. Un jour il d\u00e9couvre que son propre fils a accept\u00e9 une jolie somme d'argent pour pi\u00e9ger un dealer rival des cartels locaux. Pour le sortir de cette sale histoire, Emmet d\u00e9cide de prendre les choses en main et de monter le coup lui-m\u00eame. Mais pendant l'embuscade, il assassine un agent infiltr\u00e9 des stup ! Poursuivi \u00e0 la fois par les autorit\u00e9s f\u00e9d\u00e9rales et les chasseurs de prime, c'est le d\u00e9but d'une longue cavale dans les badlands... Avec Mexicana, Matz fait une entr\u00e9e brutale dans le catalogue Gl\u00e9nat. L'auteur du Tueur s'associe au sc\u00e9nario \u00e0 son presqu'homonyme am\u00e9ricain Mars pour nous livrer un polar noir et percutant, plus qu'efficacement mis en image par le trait nerveux de Mezzomo.", "type": "comicSeries", "publisher": "Gl\u00e9nat", "name": "Mexicana"}]}