{"metadata": [{"year": "2017", "description": "Narco Business est le 1er tome de la 2e saison d'Insiders, le redoutable thriller concoct\u00e9 par Bartoll et Garreta... Guerre sur le march\u00e9 de la drogue, luttes d'influence, \u00e9conomie parall\u00e8le, documentation tr\u00e8s pr\u00e9cise et pouss\u00e9e : les ingr\u00e9dients qui ont fait la r\u00e9ussite de la s\u00e9rie sont bien pr\u00e9sents ! Pour ce 1er album de la saison 2, on retrouve Najah, l'h\u00e9ro\u00efne d'Insiders, au Japon. ...\n\nLa redoutable jeune femme est d\u00e9sormais \u00e0 la t\u00eate du Grand Conseil des mafias et a besoin du soutien des yakuzas pour s'y maintenir. Alors qu'elle se pr\u00e9pare \u00e0 discuter avec eux, une devise ne quitte pas son esprit d'infiltr\u00e9e : \u00ab La voie du guerrier est l'acceptation de la mort. \u00bb Aux \u00c9tats-Unis, Torquemada, du cartel colombien de la drogue, est confront\u00e9 \u00e0 une OPA tr\u00e8s hostile de la part de ses homologues mexicains sur le march\u00e9 am\u00e9ricain. La guerre est d\u00e9clar\u00e9e, et le Colombien fait appel au Grand Conseil... Ce 1er volet de la 2e saison d'Insiders sera suivi de 3 autres albums.", "type": "comicSeries", "publisher": "Dargaud", "name": "Insiders"}]}