{"metadata": [{"year": "2020", "description": "La Grande Guerre brise la vie de deux hommes que tout s\u00e9parait, pourtant \u00e0 jamais li\u00e9s dans l'enfer des tranch\u00e9es, Boubacar N'Dor\u00e9 et Joseph, son ma\u00eetre dans les plantations de C\u00f4te d'Ivoire. Le premier y laissera la vie et le second ne trouvera le repos avant d'honorer une derni\u00e8re fois son camarade. En 1920, l'occasion s'offre \u00e0 lui, suite \u00e0 la d\u00e9cision d'inhumer un d\u00e9sh\u00e9rit\u00e9 de la mort sous l'Arc de triomphe...", "type": "comicSeries", "publisher": "Delcourt", "name": "L'Homme de l'ann\u00e9e"}]}