{"metadata": [{"publisher": "Le Lombard", "year": "2017", "type": "comicSeries", "description": "La Horde des Vivants faiblit face aux attaques r\u00e9p\u00e9t\u00e9es des Hittites. Leur seul espoir ne tient qu'\u00e0 un fil : s'introduire en territoire ennemi et tuer le roi. Car, selon les lois hittites, la guerre devra cesser jusqu'\u00e0 l'arriv\u00e9e d'un nouveau souverain sur le tr\u00f4ne. Thusia s'envole donc sur l'un des griffons de Marak pour la capitale hittite. Si elle r\u00e9ussit, la Horde vivra.", "name": "Reconqu\u00eates"}]}