{"metadata": [{"publisher": "Legendary", "year": "2015", "type": "comicSeries", "description": "Legendary Comics turns history on its head with the sci-fi adventure Epochalypse, a mind-bending new series from historical author Jonathan Hennessey (The United States Constitution: A Graphic Adaptation; The Gettysburg Address: A Graphic Adaptation) and acclaimed artist Shane Davis (Superman: Earth One, Shadow Walk).\n \nWhen a mysterious space-time phenomenon causes 600 years of human history to collapse into a single era, societies from the past, present and future are forced to coexist in a dystopian civilization. To set the timeline straight, an elite team of Resynchronization Officers must rid the world of Anachronisms - futuristic artifacts that threaten the very laws of time. To ensure our future, we must undo it.\n \nAs one defiant officer leads the manhunt for elusive scientist Dr. Tomorrow and notorious outlaw The Salesman, he is challenged by shadowy agencies, rebel militias and forbidden desire. Can our hero save history - or doom the future?", "name": "Epochalypse"}]}