{"metadata": [{"type": "comicSeries", "publisher": "TORICO Co., Ltd.", "year": "2019", "description": "Miyatake and Saijo, the tall freshmen from basketball club who always compete against each other on everything, have been hanging out together since junior high. After entering high school, they became closer to Komori, the tiny and gentle guy who immediately charmed both of them. Miyatake assumed Komori is interested more in Saijo who is a better basketball player, so he started avoiding his crush. Little he knows Komori might care about him more than he thought... Meanwhile, Nakatani, the giant ace from basketball club, started approaching Saijo aggressively.", "name": "Azure Chalk (Yaoi / BL Manga)"}]}