{"metadata": [{"year": "2015", "description": "Avec le chat de Cath, c\u2019est trop l\u2019\u00e9clate ! Enfin, \u00e7a d\u00e9pend : sauf les jours o\u00f9 il fait ses griffes sur la moquette, o\u00f9 il squatte le bureau de Cath et o\u00f9 il transforme les factures \u00e0 payer en boulettes de papier\u2026 Une s\u00e9rie pleine de fra\u00eecheur et de tendresse qui raconte la vie quotidienne d'un p\u00e8re c\u00e9libataire et de sa fille, aux prises avec leur f\u00e9lin un peu trop filou.", "type": "comicSeries", "publisher": "Bamboo", "name": "Cath et son chat"}]}