{"metadata": [{"publisher": "Marvel", "year": "2008", "type": "comicSeries", "description": "He's gone from the son of the one of the world's greatest villains, to one of Earth's Mightiest Heroes and then to one of the world's greatest villains in his own right. Now, Pietro Maximoff, Quicksilver, the man behind the Decimation of the world's mutants finds himself depowered and trapped in a prison cell, where he must confront all the demons of his past.", "name": "X-Factor: The Quick and the Dead"}]}