{"metadata": [{"year": "2016", "description": "Dakota du Sud, hiver 1890. Alors que l'arm\u00e9e am\u00e9ricaine s'appr\u00eate \u00e0 commettre l'un des pires massacres d'Indiens de l'histoire des \u00c9tats-Unis, le soldat Jonah sauve secr\u00e8tement la vie d'un nouveau-n\u00e9 sioux. Ulysse grandit parmi les colons blancs du Wyoming, mais ses diff\u00e9rences ne tardent pas \u00e0 l'en exclure. Il est d\u00e9j\u00e0 sur le d\u00e9part, en qu\u00eate de son identit\u00e9, d\u00e9chir\u00e9 entre ses origines et les promesses du R\u00eave am\u00e9ricain\u2026", "type": "comicSeries", "publisher": "Gallimard", "name": "Ulysse Wincoop"}]}