{"metadata": [{"year": "2010", "description": "Plus d\u00e9lirants que ceux de Saint-Tropez, plus efficaces que le GIGN, ils vont vous en faire voir de toutes les couleurs ! Gendarmes, ma\u00eetres chien, motards, maritimes ou de haute montagne... personne n'est \u00e9pargn\u00e9 par l'avalanche de gags - inspir\u00e9s de faits r\u00e9els ou tout droit sortis de l'imagination d\u00e9bordante des auteurs - qui d\u00e9baroule au fil des albums. Ceux qui ont parfois tendance \u00e0 nous faire trembler vont cette fois nous faire mourir de rire. Alors profitons-en !", "type": "comicSeries", "publisher": "Bamboo", "name": "Les Gendarmes"}]}