{"metadata": [{"publisher": "Kodansha Comics", "year": "2019", "type": "comicSeries", "description": "A covert mission in Shanghai reunites Kusanagi with a wartime rival amid shifting loyalties. The infiltration of an anti-cyberization cult calls for Section 9\u2019s most \u201chuman\u201d members to do things the old-fashioned way. A deep dive into the mind of a criminal forces Kusanagi to question the nature of imagination \u2013 and her own identity. The stories in Global Neural Network bring a 21st-century perspective to its questions of human identity and the border between mind and machine that made The Ghost in the Shell one of the most revered manga of all time, and unleash top Western comics artists on eye-popping action scenes starring Kusanagi, Batou, Togusa, Aramaki, and all the members of Section 9!\n\nOriginal stories by:\n* Alex de Campi (Twisted Romance) & Giannis Milonogiannis (Prophet)\n* Brenden Fletcher (Gotham Academy, Motor Crush) & LRNZ (Golem)\n* Genevieve Valentine (Mechanique, Icon), & Brent Schoonover (The Astonishing Ant-Man)\n* Max Gladstone (the Craft Sequence) & David L\u00f3pez (All-New Wolverine)", "name": "Ghost in the Shell: Global Neural Network"}]}