{"metadata": [{"type": "comicSeries", "publisher": "Papercutz", "year": "2019", "description": "Meet Julie, Lucy, and Alia! Whether it's ballet, modern dance, or hip-hop, these three are committed to getting better, and maybe one day making it to the Nationals! In the meantime, they still have school, family, crushes, and everything else life throws their way. Follow along with their hilarious misadventures as they practice to perfection, ace their recitals, and hopefully make it through with no bumps and bruises!", "name": "Dance Class"}]}