{"metadata": [{"publisher": "Marvel", "year": "2018", "type": "comicSeries", "description": "Collects Multiple Man #1-5.\n\nJamie Madrox is back from the dead\u2026sort of\u2026maybe? And he\u2019ll stay that way \u2014 as long as he doesn\u2019t kill himself trying to make sure he doesn\u2019t die! It makes sense when you read it \u2014 trust us. In his fight to survive, Jamie stumbles across a threat even greater than his own mortality, but fixing it might make everything worse. Can the Multiple Man save the world from himself? On top of all that, the X-Men are mad at him, and a mysterious group of foes is after him. Jamie\u2019s only hope is to go to the future \u2014 to tell himself not to go to the past! He\u2019ll soon find a few familiar faces, but a dangerous enemy threatens all his yesterdays and tomorrows! The fate of the Marvel Universe is in the hands of Jamie Madrox!\n", "name": "Multiple Man"}]}