{"metadata": [{"year": "2017", "description": "Vertiges du c\u0153ur. \u00c0 Montr\u00e9al, comme partout ailleurs, les couples se font et se d\u00e9font. Les individus s\u2019attirent, se repoussent, dans une perp\u00e9tuelle valse des corps. Dans cette m\u00eame ville s\u2019entrecroisent des destins \u00e0 la fois diff\u00e9rents et semblables, li\u00e9s par ce sentiment indescriptible : l\u2019amour. Cette inconnue \u00e0 laquelle m\u00eame la science ne peut donner d\u2019explication, ce concept qui nourrit l\u2019imaginaire des artistes depuis toujours, est au c\u0153ur du nouveau roman graphique de Julie Maroh. \u00c0 travers vingt et une nouvelles de bande dessin\u00e9e, sur 300 pages, l\u2019auteure retrace les diff\u00e9rentes \u00e9tapes d\u2019une relation amoureuse : les premiers flirts, les rendez-vous manqu\u00e9s, la vie sous le m\u00eame toit, la rupture... Interrogeant les \u00e9motions, convoquant les sens, elle d\u00e9crit les parcours de personnages criants de v\u00e9rit\u00e9. Loin des suppos\u00e9es \u00ab normes \u00bb de genre et des st\u00e9r\u00e9otypes physiques ou raciaux, leurs corps, dans leur diversit\u00e9, sont les n\u00f4tres. Avec eux, nous partageons l\u2019excitation, les doutes, la tristesse, la joie, la honte, la col\u00e8re. Comme eux, nous aimons. Corps sonores est un ouvrage \u00e0 la fois universel et r\u00e9solument contemporain dans ce qu\u2019il donne \u00e0 voir de la r\u00e9alit\u00e9 humaine.", "type": "comicSeries", "publisher": "Gl\u00e9nat", "name": "Corps sonores"}]}