{"metadata": [{"type": "comicSeries", "publisher": "TOKYOPOP", "year": "2018", "description": "Even though the wealthy young girl Miriya has almost everything she could ever need, what she really wants is the one thing money can't buy: her missing parents. But this year, she gets an extra special birthday gift when Marie, a magical white kitten, appears and whisks her away to Paris! Learning the art of magic is one thing, but getting to eat the tastiest French pastries and wear the most beautiful fashion takes Miriya and Marie's journey to a whole new level!\n", "name": "Disney Manga: Miriya and Marie"}]}