{"metadata": [{"year": "2015", "description": "Deux histoires horrifiques situ\u00e9es \u00e0 deux \u00e9poques diff\u00e9rentes et unifi\u00e9es par la maestria graphique d'Ashley Wood.\n\nCes contes horrifiques r\u00e9v\u00e8lent des facettes encore inexplor\u00e9es de la mythologie et de la mal\u00e9diction de Spawn, qu\u2019il soit croque-mitaine porteur des p\u00each\u00e9s des damn\u00e9s de la Terre ou ap\u00f4tre d\u2019une justice faite de violence et de sang.\n", "type": "comicSeries", "publisher": "Delcourt", "name": "Spawn - De sang et d'ombres"}]}