{"metadata": [{"publisher": "Marvel", "year": "2001", "type": "comicSeries", "description": "To deliver a desperate warning to the Multiverse, the living computer known as X-51 forms a team of champions selected from different realities! Behold the Heralds: Wolverine, resurrected from the Days of Future Past! Deathlok, the Machine Man! Killraven, the Warrior of The Worlds! Bloodstorm, the vampire from MUTANT X! Iron Man 2020, the corrupt nephew of Tony Stark! Hyperion, the last living member of the Squadron Supreme! Spider-Girl, the daughter of Spider-Man! But will this warning come too late? Or not soon enough? What will be the fate of this wild alternate future?\n", "name": "Paradise X: Heralds"}]}