{"metadata": [{"publisher": "Les Humano\u00efdes Associ\u00e9s", "year": "2016", "type": "comicSeries", "description": "Un r\u00e9cit po\u00e9tique et sensible, \u00e9crit pour le Mime Marceau et adapt\u00e9 par Jodorowsky et Boiscommun.. PARUTION EN 2 VOLUMES - S\u00c9RIE TERMIN\u00c9E. Pietrolino est un r\u00e9cit qui marque par sa po\u00e9sie et par la gr\u00e2ce des dessins qui l'incarnent. Cette histoire \u00e0 l'\u00e9poque de l'occupation est un r\u00e9cit hors-norme dans la bibliographie de Jodorowsky, magnifiquement servi par le dessin d'Olivier Boiscommun.. Pi\u00e8ce de th\u00e9\u00e2tre de mime \u2013 destin\u00e9e au Mime Marceau - avant d'\u00eatre sc\u00e9nario de bande dessin\u00e9e, Pietrolino est une histoire d'amour, d'art et de trahison. On y suit la destin\u00e9e contrari\u00e9e de Pietrolino, magicien enchanteur capable de faire passer toutes les \u00e9motions dans son mime, martyris\u00e9 par les nazis, trahi par la femme qu'il aime\u2026.", "name": "Pietrolino"}]}